marten/__init__.py
marten/cli.py
marten/configurations.py
marten/util.py
marten/loaded_configs/__init__.py
marten-0.6.1.dist-info/DESCRIPTION.rst
marten-0.6.1.dist-info/METADATA
marten-0.6.1.dist-info/RECORD
marten-0.6.1.dist-info/WHEEL
marten-0.6.1.dist-info/entry_points.txt
marten-0.6.1.dist-info/metadata.json
marten-0.6.1.dist-info/top_level.txt
