Metadata-Version: 2.0
Name: marten
Version: 0.6.1
Summary: Stupid simple Python configuration environments
Home-page: https://github.com/nick-allen/marten
Author: Nick Allen
Author-email: nick.allen.cse@gmail.com
License: MIT
Platform: UNKNOWN
Requires-Dist: PyYAML (>=3.0)
Requires-Dist: six (>=1.0)
Provides-Extra: test
Requires-Dist: coverage (>=4.0); extra == 'test'
Requires-Dist: coveralls (>=1.1); extra == 'test'
Requires-Dist: mock (>=1.0); extra == 'test'
Requires-Dist: nose (>=1.0); extra == 'test'
Requires-Dist: tox (>=2.1); extra == 'test'
